{
  "updatedAt": "2026-06-13 20:01",
  "players": [
    {
      "id": "oliver",
      "name": "Oliver"
    },
    {
      "id": "loui",
      "name": "Loui"
    },
    {
      "id": "lova",
      "name": "Lova"
    },
    {
      "id": "kattis",
      "name": "Kattis"
    },
    {
      "id": "emelie",
      "name": "Emelie"
    },
    {
      "id": "jens",
      "name": "Jens"
    },
    {
      "id": "per",
      "name": "Per"
    },
    {
      "id": "fredrik",
      "name": "Fredrik"
    }
  ],
  "matches": [
    {
      "id": "A1",
      "group": "A",
      "home": "Mexico",
      "away": "South Africa",
      "status": "finished",
      "resultHome": 2,
      "resultAway": 0,
      "kickoff": null,
      "apiId": null
    },
    {
      "id": "A2",
      "group": "A",
      "home": "Mexico",
      "away": "Rep. of Korea",
      "status": "scheduled",
      "resultHome": null,
      "resultAway": null,
      "kickoff": null,
      "apiId": null
    },
    {
      "id": "A3",
      "group": "A",
      "home": "Mexico",
      "away": "Czech Rep.",
      "status": "scheduled",
      "resultHome": null,
      "resultAway": null,
      "kickoff": null,
      "apiId": null
    },
    {
      "id": "A4",
      "group": "A",
      "home": "South Africa",
      "away": "Rep. of Korea",
      "status": "scheduled",
      "resultHome": null,
      "resultAway": null,
      "kickoff": null,
      "apiId": null
    },
    {
      "id": "A5",
      "group": "A",
      "home": "South Africa",
      "away": "Czech Rep.",
      "status": "scheduled",
      "resultHome": null,
      "resultAway": null,
      "kickoff": null,
      "apiId": null
    },
    {
      "id": "A6",
      "group": "A",
      "home": "Rep. of Korea",
      "away": "Czech Rep.",
      "status": "finished",
      "resultHome": 2,
      "resultAway": 1,
      "kickoff": null,
      "apiId": null
    },
    {
      "id": "B1",
      "group": "B",
      "home": "Canada",
      "away": "Bosnia/Herzeg.",
      "status": "finished",
      "resultHome": 1,
      "resultAway": 1,
      "kickoff": null,
      "apiId": null
    },
    {
      "id": "B2",
      "group": "B",
      "home": "Canada",
      "away": "Qatar",
      "status": "scheduled",
      "resultHome": null,
      "resultAway": null,
      "kickoff": null,
      "apiId": null
    },
    {
      "id": "B3",
      "group": "B",
      "home": "Canada",
      "away": "Switzerland",
      "status": "scheduled",
      "resultHome": null,
      "resultAway": null,
      "kickoff": null,
      "apiId": null
    },
    {
      "id": "B4",
      "group": "B",
      "home": "Bosnia/Herzeg.",
      "away": "Qatar",
      "status": "scheduled",
      "resultHome": null,
      "resultAway": null,
      "kickoff": null,
      "apiId": null
    },
    {
      "id": "B5",
      "group": "B",
      "home": "Bosnia/Herzeg.",
      "away": "Switzerland",
      "status": "scheduled",
      "resultHome": null,
      "resultAway": null,
      "kickoff": null,
      "apiId": null
    },
    {
      "id": "B6",
      "group": "B",
      "home": "Qatar",
      "away": "Switzerland",
      "status": "scheduled",
      "resultHome": null,
      "resultAway": null,
      "kickoff": null,
      "apiId": null
    },
    {
      "id": "C1",
      "group": "C",
      "home": "Brazil",
      "away": "Morocco",
      "status": "scheduled",
      "resultHome": null,
      "resultAway": null,
      "kickoff": null,
      "apiId": null
    },
    {
      "id": "C2",
      "group": "C",
      "home": "Brazil",
      "away": "Haiti",
      "status": "scheduled",
      "resultHome": null,
      "resultAway": null,
      "kickoff": null,
      "apiId": null
    },
    {
      "id": "C3",
      "group": "C",
      "home": "Brazil",
      "away": "Scotland",
      "status": "scheduled",
      "resultHome": null,
      "resultAway": null,
      "kickoff": null,
      "apiId": null
    },
    {
      "id": "C4",
      "group": "C",
      "home": "Morocco",
      "away": "Haiti",
      "status": "scheduled",
      "resultHome": null,
      "resultAway": null,
      "kickoff": null,
      "apiId": null
    },
    {
      "id": "C5",
      "group": "C",
      "home": "Morocco",
      "away": "Scotland",
      "status": "scheduled",
      "resultHome": null,
      "resultAway": null,
      "kickoff": null,
      "apiId": null
    },
    {
      "id": "C6",
      "group": "C",
      "home": "Haiti",
      "away": "Scotland",
      "status": "scheduled",
      "resultHome": null,
      "resultAway": null,
      "kickoff": null,
      "apiId": null
    },
    {
      "id": "D1",
      "group": "D",
      "home": "USA",
      "away": "Paraguay",
      "status": "finished",
      "resultHome": 4,
      "resultAway": 1,
      "kickoff": null,
      "apiId": null
    },
    {
      "id": "D2",
      "group": "D",
      "home": "USA",
      "away": "Australia",
      "status": "scheduled",
      "resultHome": null,
      "resultAway": null,
      "kickoff": null,
      "apiId": null
    },
    {
      "id": "D3",
      "group": "D",
      "home": "USA",
      "away": "Turkey",
      "status": "scheduled",
      "resultHome": null,
      "resultAway": null,
      "kickoff": null,
      "apiId": null
    },
    {
      "id": "D4",
      "group": "D",
      "home": "Paraguay",
      "away": "Australia",
      "status": "scheduled",
      "resultHome": null,
      "resultAway": null,
      "kickoff": null,
      "apiId": null
    },
    {
      "id": "D5",
      "group": "D",
      "home": "Paraguay",
      "away": "Turkey",
      "status": "scheduled",
      "resultHome": null,
      "resultAway": null,
      "kickoff": null,
      "apiId": null
    },
    {
      "id": "D6",
      "group": "D",
      "home": "Australia",
      "away": "Turkey",
      "status": "scheduled",
      "resultHome": null,
      "resultAway": null,
      "kickoff": null,
      "apiId": null
    },
    {
      "id": "E1",
      "group": "E",
      "home": "Germany",
      "away": "Curaçao",
      "status": "scheduled",
      "resultHome": null,
      "resultAway": null,
      "kickoff": null,
      "apiId": null
    },
    {
      "id": "E2",
      "group": "E",
      "home": "Germany",
      "away": "Ivory Coast",
      "status": "scheduled",
      "resultHome": null,
      "resultAway": null,
      "kickoff": null,
      "apiId": null
    },
    {
      "id": "E3",
      "group": "E",
      "home": "Germany",
      "away": "Ecuador",
      "status": "scheduled",
      "resultHome": null,
      "resultAway": null,
      "kickoff": null,
      "apiId": null
    },
    {
      "id": "E4",
      "group": "E",
      "home": "Curaçao",
      "away": "Ivory Coast",
      "status": "scheduled",
      "resultHome": null,
      "resultAway": null,
      "kickoff": null,
      "apiId": null
    },
    {
      "id": "E5",
      "group": "E",
      "home": "Curaçao",
      "away": "Ecuador",
      "status": "scheduled",
      "resultHome": null,
      "resultAway": null,
      "kickoff": null,
      "apiId": null
    },
    {
      "id": "E6",
      "group": "E",
      "home": "Ivory Coast",
      "away": "Ecuador",
      "status": "scheduled",
      "resultHome": null,
      "resultAway": null,
      "kickoff": null,
      "apiId": null
    },
    {
      "id": "F1",
      "group": "F",
      "home": "Netherlands",
      "away": "Japan",
      "status": "scheduled",
      "resultHome": null,
      "resultAway": null,
      "kickoff": null,
      "apiId": null
    },
    {
      "id": "F2",
      "group": "F",
      "home": "Netherlands",
      "away": "Sweden",
      "status": "scheduled",
      "resultHome": null,
      "resultAway": null,
      "kickoff": null,
      "apiId": null
    },
    {
      "id": "F3",
      "group": "F",
      "home": "Netherlands",
      "away": "Tunisia",
      "status": "scheduled",
      "resultHome": null,
      "resultAway": null,
      "kickoff": null,
      "apiId": null
    },
    {
      "id": "F4",
      "group": "F",
      "home": "Japan",
      "away": "Sweden",
      "status": "scheduled",
      "resultHome": null,
      "resultAway": null,
      "kickoff": null,
      "apiId": null
    },
    {
      "id": "F5",
      "group": "F",
      "home": "Japan",
      "away": "Tunisia",
      "status": "scheduled",
      "resultHome": null,
      "resultAway": null,
      "kickoff": null,
      "apiId": null
    },
    {
      "id": "F6",
      "group": "F",
      "home": "Sweden",
      "away": "Tunisia",
      "status": "scheduled",
      "resultHome": null,
      "resultAway": null,
      "kickoff": null,
      "apiId": null
    },
    {
      "id": "G1",
      "group": "G",
      "home": "Belgium",
      "away": "Egypt",
      "status": "scheduled",
      "resultHome": null,
      "resultAway": null,
      "kickoff": null,
      "apiId": null
    },
    {
      "id": "G2",
      "group": "G",
      "home": "Belgium",
      "away": "IR Iran",
      "status": "scheduled",
      "resultHome": null,
      "resultAway": null,
      "kickoff": null,
      "apiId": null
    },
    {
      "id": "G3",
      "group": "G",
      "home": "Belgium",
      "away": "New Zealand",
      "status": "scheduled",
      "resultHome": null,
      "resultAway": null,
      "kickoff": null,
      "apiId": null
    },
    {
      "id": "G4",
      "group": "G",
      "home": "Egypt",
      "away": "IR Iran",
      "status": "scheduled",
      "resultHome": null,
      "resultAway": null,
      "kickoff": null,
      "apiId": null
    },
    {
      "id": "G5",
      "group": "G",
      "home": "Egypt",
      "away": "New Zealand",
      "status": "scheduled",
      "resultHome": null,
      "resultAway": null,
      "kickoff": null,
      "apiId": null
    },
    {
      "id": "G6",
      "group": "G",
      "home": "IR Iran",
      "away": "New Zealand",
      "status": "scheduled",
      "resultHome": null,
      "resultAway": null,
      "kickoff": null,
      "apiId": null
    },
    {
      "id": "H1",
      "group": "H",
      "home": "Spain",
      "away": "Cape Verde",
      "status": "scheduled",
      "resultHome": null,
      "resultAway": null,
      "kickoff": null,
      "apiId": null
    },
    {
      "id": "H2",
      "group": "H",
      "home": "Spain",
      "away": "Saudi Arabia",
      "status": "scheduled",
      "resultHome": null,
      "resultAway": null,
      "kickoff": null,
      "apiId": null
    },
    {
      "id": "H3",
      "group": "H",
      "home": "Spain",
      "away": "Uruguay",
      "status": "scheduled",
      "resultHome": null,
      "resultAway": null,
      "kickoff": null,
      "apiId": null
    },
    {
      "id": "H4",
      "group": "H",
      "home": "Cape Verde",
      "away": "Saudi Arabia",
      "status": "scheduled",
      "resultHome": null,
      "resultAway": null,
      "kickoff": null,
      "apiId": null
    },
    {
      "id": "H5",
      "group": "H",
      "home": "Cape Verde",
      "away": "Uruguay",
      "status": "scheduled",
      "resultHome": null,
      "resultAway": null,
      "kickoff": null,
      "apiId": null
    },
    {
      "id": "H6",
      "group": "H",
      "home": "Saudi Arabia",
      "away": "Uruguay",
      "status": "scheduled",
      "resultHome": null,
      "resultAway": null,
      "kickoff": null,
      "apiId": null
    },
    {
      "id": "I1",
      "group": "I",
      "home": "France",
      "away": "Senegal",
      "status": "scheduled",
      "resultHome": null,
      "resultAway": null,
      "kickoff": null,
      "apiId": null
    },
    {
      "id": "I2",
      "group": "I",
      "home": "France",
      "away": "Iraq",
      "status": "scheduled",
      "resultHome": null,
      "resultAway": null,
      "kickoff": null,
      "apiId": null
    },
    {
      "id": "I3",
      "group": "I",
      "home": "France",
      "away": "Norway",
      "status": "scheduled",
      "resultHome": null,
      "resultAway": null,
      "kickoff": null,
      "apiId": null
    },
    {
      "id": "I4",
      "group": "I",
      "home": "Senegal",
      "away": "Iraq",
      "status": "scheduled",
      "resultHome": null,
      "resultAway": null,
      "kickoff": null,
      "apiId": null
    },
    {
      "id": "I5",
      "group": "I",
      "home": "Senegal",
      "away": "Norway",
      "status": "scheduled",
      "resultHome": null,
      "resultAway": null,
      "kickoff": null,
      "apiId": null
    },
    {
      "id": "I6",
      "group": "I",
      "home": "Iraq",
      "away": "Norway",
      "status": "scheduled",
      "resultHome": null,
      "resultAway": null,
      "kickoff": null,
      "apiId": null
    },
    {
      "id": "J1",
      "group": "J",
      "home": "Argentina",
      "away": "Algeria",
      "status": "scheduled",
      "resultHome": null,
      "resultAway": null,
      "kickoff": null,
      "apiId": null
    },
    {
      "id": "J2",
      "group": "J",
      "home": "Argentina",
      "away": "Austria",
      "status": "scheduled",
      "resultHome": null,
      "resultAway": null,
      "kickoff": null,
      "apiId": null
    },
    {
      "id": "J3",
      "group": "J",
      "home": "Argentina",
      "away": "Jordan",
      "status": "scheduled",
      "resultHome": null,
      "resultAway": null,
      "kickoff": null,
      "apiId": null
    },
    {
      "id": "J4",
      "group": "J",
      "home": "Algeria",
      "away": "Austria",
      "status": "scheduled",
      "resultHome": null,
      "resultAway": null,
      "kickoff": null,
      "apiId": null
    },
    {
      "id": "J5",
      "group": "J",
      "home": "Algeria",
      "away": "Jordan",
      "status": "scheduled",
      "resultHome": null,
      "resultAway": null,
      "kickoff": null,
      "apiId": null
    },
    {
      "id": "J6",
      "group": "J",
      "home": "Austria",
      "away": "Jordan",
      "status": "scheduled",
      "resultHome": null,
      "resultAway": null,
      "kickoff": null,
      "apiId": null
    },
    {
      "id": "K1",
      "group": "K",
      "home": "Portugal",
      "away": "DR Congo",
      "status": "scheduled",
      "resultHome": null,
      "resultAway": null,
      "kickoff": null,
      "apiId": null
    },
    {
      "id": "K2",
      "group": "K",
      "home": "Portugal",
      "away": "Uzbekistan",
      "status": "scheduled",
      "resultHome": null,
      "resultAway": null,
      "kickoff": null,
      "apiId": null
    },
    {
      "id": "K3",
      "group": "K",
      "home": "Portugal",
      "away": "Colombia",
      "status": "scheduled",
      "resultHome": null,
      "resultAway": null,
      "kickoff": null,
      "apiId": null
    },
    {
      "id": "K4",
      "group": "K",
      "home": "DR Congo",
      "away": "Uzbekistan",
      "status": "scheduled",
      "resultHome": null,
      "resultAway": null,
      "kickoff": null,
      "apiId": null
    },
    {
      "id": "K5",
      "group": "K",
      "home": "DR Congo",
      "away": "Colombia",
      "status": "scheduled",
      "resultHome": null,
      "resultAway": null,
      "kickoff": null,
      "apiId": null
    },
    {
      "id": "K6",
      "group": "K",
      "home": "Uzbekistan",
      "away": "Colombia",
      "status": "scheduled",
      "resultHome": null,
      "resultAway": null,
      "kickoff": null,
      "apiId": null
    },
    {
      "id": "L1",
      "group": "L",
      "home": "England",
      "away": "Croatia",
      "status": "scheduled",
      "resultHome": null,
      "resultAway": null,
      "kickoff": null,
      "apiId": null
    },
    {
      "id": "L2",
      "group": "L",
      "home": "England",
      "away": "Ghana",
      "status": "scheduled",
      "resultHome": null,
      "resultAway": null,
      "kickoff": null,
      "apiId": null
    },
    {
      "id": "L3",
      "group": "L",
      "home": "England",
      "away": "Panama",
      "status": "scheduled",
      "resultHome": null,
      "resultAway": null,
      "kickoff": null,
      "apiId": null
    },
    {
      "id": "L4",
      "group": "L",
      "home": "Croatia",
      "away": "Ghana",
      "status": "scheduled",
      "resultHome": null,
      "resultAway": null,
      "kickoff": null,
      "apiId": null
    },
    {
      "id": "L5",
      "group": "L",
      "home": "Croatia",
      "away": "Panama",
      "status": "scheduled",
      "resultHome": null,
      "resultAway": null,
      "kickoff": null,
      "apiId": null
    },
    {
      "id": "L6",
      "group": "L",
      "home": "Ghana",
      "away": "Panama",
      "status": "scheduled",
      "resultHome": null,
      "resultAway": null,
      "kickoff": null,
      "apiId": null
    }
  ],
  "predictions": [
    {
      "playerId": "oliver",
      "matchId": "A1",
      "home": 3,
      "away": 0
    },
    {
      "playerId": "oliver",
      "matchId": "A2",
      "home": 1,
      "away": 1
    },
    {
      "playerId": "oliver",
      "matchId": "A3",
      "home": 2,
      "away": 0
    },
    {
      "playerId": "oliver",
      "matchId": "A4",
      "home": 0,
      "away": 1
    },
    {
      "playerId": "oliver",
      "matchId": "A5",
      "home": 2,
      "away": 1
    },
    {
      "playerId": "oliver",
      "matchId": "A6",
      "home": 2,
      "away": 0
    },
    {
      "playerId": "oliver",
      "matchId": "B1",
      "home": 1,
      "away": 0
    },
    {
      "playerId": "oliver",
      "matchId": "B2",
      "home": 2,
      "away": 1
    },
    {
      "playerId": "oliver",
      "matchId": "B3",
      "home": 3,
      "away": 1
    },
    {
      "playerId": "oliver",
      "matchId": "B4",
      "home": 1,
      "away": 0
    },
    {
      "playerId": "oliver",
      "matchId": "B5",
      "home": 0,
      "away": 2
    },
    {
      "playerId": "oliver",
      "matchId": "B6",
      "home": 0,
      "away": 1
    },
    {
      "playerId": "oliver",
      "matchId": "C1",
      "home": 2,
      "away": 1
    },
    {
      "playerId": "oliver",
      "matchId": "C2",
      "home": 4,
      "away": 0
    },
    {
      "playerId": "oliver",
      "matchId": "C3",
      "home": 2,
      "away": 0
    },
    {
      "playerId": "oliver",
      "matchId": "C4",
      "home": 2,
      "away": 0
    },
    {
      "playerId": "oliver",
      "matchId": "C5",
      "home": 1,
      "away": 0
    },
    {
      "playerId": "oliver",
      "matchId": "C6",
      "home": 0,
      "away": 2
    },
    {
      "playerId": "oliver",
      "matchId": "D1",
      "home": 1,
      "away": 1
    },
    {
      "playerId": "oliver",
      "matchId": "D2",
      "home": 1,
      "away": 0
    },
    {
      "playerId": "oliver",
      "matchId": "D3",
      "home": 0,
      "away": 2
    },
    {
      "playerId": "oliver",
      "matchId": "D4",
      "home": 2,
      "away": 1
    },
    {
      "playerId": "oliver",
      "matchId": "D5",
      "home": 2,
      "away": 3
    },
    {
      "playerId": "oliver",
      "matchId": "D6",
      "home": 1,
      "away": 0
    },
    {
      "playerId": "oliver",
      "matchId": "E1",
      "home": 3,
      "away": 0
    },
    {
      "playerId": "oliver",
      "matchId": "E2",
      "home": 2,
      "away": 1
    },
    {
      "playerId": "oliver",
      "matchId": "E3",
      "home": 2,
      "away": 0
    },
    {
      "playerId": "oliver",
      "matchId": "E4",
      "home": 0,
      "away": 1
    },
    {
      "playerId": "oliver",
      "matchId": "E5",
      "home": 1,
      "away": 1
    },
    {
      "playerId": "oliver",
      "matchId": "E6",
      "home": 1,
      "away": 2
    },
    {
      "playerId": "oliver",
      "matchId": "F1",
      "home": 3,
      "away": 1
    },
    {
      "playerId": "oliver",
      "matchId": "F2",
      "home": 2,
      "away": 0
    },
    {
      "playerId": "oliver",
      "matchId": "F3",
      "home": 3,
      "away": 0
    },
    {
      "playerId": "oliver",
      "matchId": "F4",
      "home": 1,
      "away": 2
    },
    {
      "playerId": "oliver",
      "matchId": "F5",
      "home": 1,
      "away": 1
    },
    {
      "playerId": "oliver",
      "matchId": "F6",
      "home": 2,
      "away": 0
    },
    {
      "playerId": "oliver",
      "matchId": "G1",
      "home": 2,
      "away": 2
    },
    {
      "playerId": "oliver",
      "matchId": "G2",
      "home": 2,
      "away": 0
    },
    {
      "playerId": "oliver",
      "matchId": "G3",
      "home": 1,
      "away": 0
    },
    {
      "playerId": "oliver",
      "matchId": "G4",
      "home": 2,
      "away": 0
    },
    {
      "playerId": "oliver",
      "matchId": "G5",
      "home": 0,
      "away": 0
    },
    {
      "playerId": "oliver",
      "matchId": "G6",
      "home": 0,
      "away": 1
    },
    {
      "playerId": "oliver",
      "matchId": "H1",
      "home": 3,
      "away": 0
    },
    {
      "playerId": "oliver",
      "matchId": "H2",
      "home": 3,
      "away": 0
    },
    {
      "playerId": "oliver",
      "matchId": "H3",
      "home": 2,
      "away": 0
    },
    {
      "playerId": "oliver",
      "matchId": "H4",
      "home": 1,
      "away": 2
    },
    {
      "playerId": "oliver",
      "matchId": "H5",
      "home": 0,
      "away": 2
    },
    {
      "playerId": "oliver",
      "matchId": "H6",
      "home": 1,
      "away": 1
    },
    {
      "playerId": "oliver",
      "matchId": "I1",
      "home": 4,
      "away": 0
    },
    {
      "playerId": "oliver",
      "matchId": "I2",
      "home": 2,
      "away": 0
    },
    {
      "playerId": "oliver",
      "matchId": "I3",
      "home": 3,
      "away": 1
    },
    {
      "playerId": "oliver",
      "matchId": "I4",
      "home": 2,
      "away": 0
    },
    {
      "playerId": "oliver",
      "matchId": "I5",
      "home": 0,
      "away": 1
    },
    {
      "playerId": "oliver",
      "matchId": "I6",
      "home": 0,
      "away": 2
    },
    {
      "playerId": "oliver",
      "matchId": "J1",
      "home": 2,
      "away": 1
    },
    {
      "playerId": "oliver",
      "matchId": "J2",
      "home": 2,
      "away": 0
    },
    {
      "playerId": "oliver",
      "matchId": "J3",
      "home": 4,
      "away": 1
    },
    {
      "playerId": "oliver",
      "matchId": "J4",
      "home": 0,
      "away": 2
    },
    {
      "playerId": "oliver",
      "matchId": "J5",
      "home": 2,
      "away": 2
    },
    {
      "playerId": "oliver",
      "matchId": "J6",
      "home": 1,
      "away": 0
    },
    {
      "playerId": "oliver",
      "matchId": "K1",
      "home": 2,
      "away": 0
    },
    {
      "playerId": "oliver",
      "matchId": "K2",
      "home": 1,
      "away": 0
    },
    {
      "playerId": "oliver",
      "matchId": "K3",
      "home": 3,
      "away": 1
    },
    {
      "playerId": "oliver",
      "matchId": "K4",
      "home": 1,
      "away": 2
    },
    {
      "playerId": "oliver",
      "matchId": "K5",
      "home": 1,
      "away": 3
    },
    {
      "playerId": "oliver",
      "matchId": "K6",
      "home": 0,
      "away": 1
    },
    {
      "playerId": "oliver",
      "matchId": "L1",
      "home": 3,
      "away": 1
    },
    {
      "playerId": "oliver",
      "matchId": "L2",
      "home": 2,
      "away": 0
    },
    {
      "playerId": "oliver",
      "matchId": "L3",
      "home": 3,
      "away": 0
    },
    {
      "playerId": "oliver",
      "matchId": "L4",
      "home": 1,
      "away": 0
    },
    {
      "playerId": "oliver",
      "matchId": "L5",
      "home": 1,
      "away": 1
    },
    {
      "playerId": "oliver",
      "matchId": "L6",
      "home": 2,
      "away": 0
    },
    {
      "playerId": "loui",
      "matchId": "A1",
      "home": 2,
      "away": 1
    },
    {
      "playerId": "loui",
      "matchId": "A2",
      "home": 2,
      "away": 1
    },
    {
      "playerId": "loui",
      "matchId": "A3",
      "home": 2,
      "away": 0
    },
    {
      "playerId": "loui",
      "matchId": "A4",
      "home": 0,
      "away": 3
    },
    {
      "playerId": "loui",
      "matchId": "A5",
      "home": 0,
      "away": 2
    },
    {
      "playerId": "loui",
      "matchId": "A6",
      "home": 2,
      "away": 1
    },
    {
      "playerId": "loui",
      "matchId": "B1",
      "home": 1,
      "away": 3
    },
    {
      "playerId": "loui",
      "matchId": "B2",
      "home": 3,
      "away": 0
    },
    {
      "playerId": "loui",
      "matchId": "B3",
      "home": 1,
      "away": 3
    },
    {
      "playerId": "loui",
      "matchId": "B4",
      "home": 3,
      "away": 0
    },
    {
      "playerId": "loui",
      "matchId": "B5",
      "home": 1,
      "away": 0
    },
    {
      "playerId": "loui",
      "matchId": "B6",
      "home": 0,
      "away": 3
    },
    {
      "playerId": "loui",
      "matchId": "C1",
      "home": 3,
      "away": 2
    },
    {
      "playerId": "loui",
      "matchId": "C2",
      "home": 5,
      "away": 0
    },
    {
      "playerId": "loui",
      "matchId": "C3",
      "home": 0,
      "away": 2
    },
    {
      "playerId": "loui",
      "matchId": "C4",
      "home": 4,
      "away": 0
    },
    {
      "playerId": "loui",
      "matchId": "C5",
      "home": 1,
      "away": 1
    },
    {
      "playerId": "loui",
      "matchId": "C6",
      "home": 0,
      "away": 3
    },
    {
      "playerId": "loui",
      "matchId": "D1",
      "home": 2,
      "away": 1
    },
    {
      "playerId": "loui",
      "matchId": "D2",
      "home": 2,
      "away": 0
    },
    {
      "playerId": "loui",
      "matchId": "D3",
      "home": 0,
      "away": 1
    },
    {
      "playerId": "loui",
      "matchId": "D4",
      "home": 1,
      "away": 2
    },
    {
      "playerId": "loui",
      "matchId": "D5",
      "home": 1,
      "away": 3
    },
    {
      "playerId": "loui",
      "matchId": "D6",
      "home": 2,
      "away": 3
    },
    {
      "playerId": "loui",
      "matchId": "E1",
      "home": 6,
      "away": 0
    },
    {
      "playerId": "loui",
      "matchId": "E2",
      "home": 5,
      "away": 0
    },
    {
      "playerId": "loui",
      "matchId": "E3",
      "home": 2,
      "away": 1
    },
    {
      "playerId": "loui",
      "matchId": "E4",
      "home": 0,
      "away": 2
    },
    {
      "playerId": "loui",
      "matchId": "E5",
      "home": 0,
      "away": 2
    },
    {
      "playerId": "loui",
      "matchId": "E6",
      "home": 2,
      "away": 2
    },
    {
      "playerId": "loui",
      "matchId": "F1",
      "home": 3,
      "away": 1
    },
    {
      "playerId": "loui",
      "matchId": "F2",
      "home": 3,
      "away": 2
    },
    {
      "playerId": "loui",
      "matchId": "F3",
      "home": 4,
      "away": 0
    },
    {
      "playerId": "loui",
      "matchId": "F4",
      "home": 1,
      "away": 3
    },
    {
      "playerId": "loui",
      "matchId": "F5",
      "home": 2,
      "away": 0
    },
    {
      "playerId": "loui",
      "matchId": "F6",
      "home": 3,
      "away": 1
    },
    {
      "playerId": "loui",
      "matchId": "G1",
      "home": 4,
      "away": 1
    },
    {
      "playerId": "loui",
      "matchId": "G2",
      "home": 6,
      "away": 0
    },
    {
      "playerId": "loui",
      "matchId": "G3",
      "home": 3,
      "away": 0
    },
    {
      "playerId": "loui",
      "matchId": "G4",
      "home": 2,
      "away": 0
    },
    {
      "playerId": "loui",
      "matchId": "G5",
      "home": 3,
      "away": 0
    },
    {
      "playerId": "loui",
      "matchId": "G6",
      "home": 2,
      "away": 1
    },
    {
      "playerId": "loui",
      "matchId": "H1",
      "home": 7,
      "away": 1
    },
    {
      "playerId": "loui",
      "matchId": "H2",
      "home": 6,
      "away": 0
    },
    {
      "playerId": "loui",
      "matchId": "H3",
      "home": 4,
      "away": 1
    },
    {
      "playerId": "loui",
      "matchId": "H4",
      "home": 2,
      "away": 2
    },
    {
      "playerId": "loui",
      "matchId": "H5",
      "home": 0,
      "away": 3
    },
    {
      "playerId": "loui",
      "matchId": "H6",
      "home": 1,
      "away": 2
    },
    {
      "playerId": "loui",
      "matchId": "I1",
      "home": 4,
      "away": 1
    },
    {
      "playerId": "loui",
      "matchId": "I2",
      "home": 6,
      "away": 0
    },
    {
      "playerId": "loui",
      "matchId": "I3",
      "home": 4,
      "away": 2
    },
    {
      "playerId": "loui",
      "matchId": "I4",
      "home": 1,
      "away": 0
    },
    {
      "playerId": "loui",
      "matchId": "I5",
      "home": 0,
      "away": 3
    },
    {
      "playerId": "loui",
      "matchId": "I6",
      "home": 0,
      "away": 2
    },
    {
      "playerId": "loui",
      "matchId": "J1",
      "home": 5,
      "away": 0
    },
    {
      "playerId": "loui",
      "matchId": "J2",
      "home": 2,
      "away": 0
    },
    {
      "playerId": "loui",
      "matchId": "J3",
      "home": 6,
      "away": 0
    },
    {
      "playerId": "loui",
      "matchId": "J4",
      "home": 2,
      "away": 0
    },
    {
      "playerId": "loui",
      "matchId": "J5",
      "home": 1,
      "away": 0
    },
    {
      "playerId": "loui",
      "matchId": "J6",
      "home": 3,
      "away": 1
    },
    {
      "playerId": "loui",
      "matchId": "K1",
      "home": 4,
      "away": 0
    },
    {
      "playerId": "loui",
      "matchId": "K2",
      "home": 4,
      "away": 1
    },
    {
      "playerId": "loui",
      "matchId": "K3",
      "home": 3,
      "away": 1
    },
    {
      "playerId": "loui",
      "matchId": "K4",
      "home": 0,
      "away": 2
    },
    {
      "playerId": "loui",
      "matchId": "K5",
      "home": 0,
      "away": 3
    },
    {
      "playerId": "loui",
      "matchId": "K6",
      "home": 1,
      "away": 2
    },
    {
      "playerId": "loui",
      "matchId": "L1",
      "home": 2,
      "away": 2
    },
    {
      "playerId": "loui",
      "matchId": "L2",
      "home": 3,
      "away": 1
    },
    {
      "playerId": "loui",
      "matchId": "L3",
      "home": 5,
      "away": 0
    },
    {
      "playerId": "loui",
      "matchId": "L4",
      "home": 3,
      "away": 0
    },
    {
      "playerId": "loui",
      "matchId": "L5",
      "home": 2,
      "away": 0
    },
    {
      "playerId": "loui",
      "matchId": "L6",
      "home": 2,
      "away": 2
    },
    {
      "playerId": "lova",
      "matchId": "A1",
      "home": 3,
      "away": 0
    },
    {
      "playerId": "lova",
      "matchId": "A2",
      "home": 2,
      "away": 2
    },
    {
      "playerId": "lova",
      "matchId": "A3",
      "home": 2,
      "away": 0
    },
    {
      "playerId": "lova",
      "matchId": "A4",
      "home": 1,
      "away": 3
    },
    {
      "playerId": "lova",
      "matchId": "A5",
      "home": 0,
      "away": 1
    },
    {
      "playerId": "lova",
      "matchId": "A6",
      "home": 1,
      "away": 1
    },
    {
      "playerId": "lova",
      "matchId": "B1",
      "home": 1,
      "away": 0
    },
    {
      "playerId": "lova",
      "matchId": "B2",
      "home": 2,
      "away": 0
    },
    {
      "playerId": "lova",
      "matchId": "B3",
      "home": 0,
      "away": 3
    },
    {
      "playerId": "lova",
      "matchId": "B4",
      "home": 1,
      "away": 1
    },
    {
      "playerId": "lova",
      "matchId": "B5",
      "home": 0,
      "away": 2
    },
    {
      "playerId": "lova",
      "matchId": "B6",
      "home": 0,
      "away": 4
    },
    {
      "playerId": "lova",
      "matchId": "C1",
      "home": 2,
      "away": 1
    },
    {
      "playerId": "lova",
      "matchId": "C2",
      "home": 4,
      "away": 0
    },
    {
      "playerId": "lova",
      "matchId": "C3",
      "home": 3,
      "away": 0
    },
    {
      "playerId": "lova",
      "matchId": "C4",
      "home": 2,
      "away": 0
    },
    {
      "playerId": "lova",
      "matchId": "C5",
      "home": 1,
      "away": 0
    },
    {
      "playerId": "lova",
      "matchId": "C6",
      "home": 0,
      "away": 1
    },
    {
      "playerId": "lova",
      "matchId": "D1",
      "home": 0,
      "away": 1
    },
    {
      "playerId": "lova",
      "matchId": "D2",
      "home": 1,
      "away": 2
    },
    {
      "playerId": "lova",
      "matchId": "D3",
      "home": 2,
      "away": 0
    },
    {
      "playerId": "lova",
      "matchId": "D4",
      "home": 0,
      "away": 0
    },
    {
      "playerId": "lova",
      "matchId": "D5",
      "home": 1,
      "away": 0
    },
    {
      "playerId": "lova",
      "matchId": "D6",
      "home": 1,
      "away": 0
    },
    {
      "playerId": "lova",
      "matchId": "E1",
      "home": 3,
      "away": 0
    },
    {
      "playerId": "lova",
      "matchId": "E2",
      "home": 2,
      "away": 1
    },
    {
      "playerId": "lova",
      "matchId": "E3",
      "home": 1,
      "away": 1
    },
    {
      "playerId": "lova",
      "matchId": "E4",
      "home": 0,
      "away": 2
    },
    {
      "playerId": "lova",
      "matchId": "E5",
      "home": 1,
      "away": 3
    },
    {
      "playerId": "lova",
      "matchId": "E6",
      "home": 2,
      "away": 2
    },
    {
      "playerId": "lova",
      "matchId": "F1",
      "home": 0,
      "away": 1
    },
    {
      "playerId": "lova",
      "matchId": "F2",
      "home": 2,
      "away": 0
    },
    {
      "playerId": "lova",
      "matchId": "F3",
      "home": 3,
      "away": 1
    },
    {
      "playerId": "lova",
      "matchId": "F4",
      "home": 1,
      "away": 0
    },
    {
      "playerId": "lova",
      "matchId": "F5",
      "home": 2,
      "away": 0
    },
    {
      "playerId": "lova",
      "matchId": "F6",
      "home": 2,
      "away": 1
    },
    {
      "playerId": "lova",
      "matchId": "G1",
      "home": 2,
      "away": 2
    },
    {
      "playerId": "lova",
      "matchId": "G2",
      "home": 1,
      "away": 0
    },
    {
      "playerId": "lova",
      "matchId": "G3",
      "home": 2,
      "away": 0
    },
    {
      "playerId": "lova",
      "matchId": "G4",
      "home": 1,
      "away": 0
    },
    {
      "playerId": "lova",
      "matchId": "G5",
      "home": 2,
      "away": 1
    },
    {
      "playerId": "lova",
      "matchId": "G6",
      "home": 3,
      "away": 1
    },
    {
      "playerId": "lova",
      "matchId": "H1",
      "home": 3,
      "away": 0
    },
    {
      "playerId": "lova",
      "matchId": "H2",
      "home": 4,
      "away": 0
    },
    {
      "playerId": "lova",
      "matchId": "H3",
      "home": 2,
      "away": 1
    },
    {
      "playerId": "lova",
      "matchId": "H4",
      "home": 0,
      "away": 0
    },
    {
      "playerId": "lova",
      "matchId": "H5",
      "home": 0,
      "away": 3
    },
    {
      "playerId": "lova",
      "matchId": "H6",
      "home": 0,
      "away": 2
    },
    {
      "playerId": "lova",
      "matchId": "I1",
      "home": 2,
      "away": 1
    },
    {
      "playerId": "lova",
      "matchId": "I2",
      "home": 4,
      "away": 0
    },
    {
      "playerId": "lova",
      "matchId": "I3",
      "home": 3,
      "away": 2
    },
    {
      "playerId": "lova",
      "matchId": "I4",
      "home": 3,
      "away": 1
    },
    {
      "playerId": "lova",
      "matchId": "I5",
      "home": 1,
      "away": 0
    },
    {
      "playerId": "lova",
      "matchId": "I6",
      "home": 0,
      "away": 2
    },
    {
      "playerId": "lova",
      "matchId": "J1",
      "home": 3,
      "away": 1
    },
    {
      "playerId": "lova",
      "matchId": "J2",
      "home": 2,
      "away": 1
    },
    {
      "playerId": "lova",
      "matchId": "J3",
      "home": 4,
      "away": 0
    },
    {
      "playerId": "lova",
      "matchId": "J4",
      "home": 1,
      "away": 1
    },
    {
      "playerId": "lova",
      "matchId": "J5",
      "home": 2,
      "away": 1
    },
    {
      "playerId": "lova",
      "matchId": "J6",
      "home": 2,
      "away": 0
    },
    {
      "playerId": "lova",
      "matchId": "K1",
      "home": 3,
      "away": 1
    },
    {
      "playerId": "lova",
      "matchId": "K2",
      "home": 3,
      "away": 0
    },
    {
      "playerId": "lova",
      "matchId": "K3",
      "home": 1,
      "away": 2
    },
    {
      "playerId": "lova",
      "matchId": "K4",
      "home": 1,
      "away": 0
    },
    {
      "playerId": "lova",
      "matchId": "K5",
      "home": 1,
      "away": 3
    },
    {
      "playerId": "lova",
      "matchId": "K6",
      "home": 1,
      "away": 4
    },
    {
      "playerId": "lova",
      "matchId": "L1",
      "home": 3,
      "away": 2
    },
    {
      "playerId": "lova",
      "matchId": "L2",
      "home": 1,
      "away": 0
    },
    {
      "playerId": "lova",
      "matchId": "L3",
      "home": 3,
      "away": 0
    },
    {
      "playerId": "lova",
      "matchId": "L4",
      "home": 2,
      "away": 1
    },
    {
      "playerId": "lova",
      "matchId": "L5",
      "home": 3,
      "away": 0
    },
    {
      "playerId": "lova",
      "matchId": "L6",
      "home": 2,
      "away": 1
    },
    {
      "playerId": "kattis",
      "matchId": "A1",
      "home": 2,
      "away": 0
    },
    {
      "playerId": "kattis",
      "matchId": "A2",
      "home": 2,
      "away": 1
    },
    {
      "playerId": "kattis",
      "matchId": "A3",
      "home": 2,
      "away": 1
    },
    {
      "playerId": "kattis",
      "matchId": "A4",
      "home": 1,
      "away": 2
    },
    {
      "playerId": "kattis",
      "matchId": "A5",
      "home": 0,
      "away": 2
    },
    {
      "playerId": "kattis",
      "matchId": "A6",
      "home": 1,
      "away": 1
    },
    {
      "playerId": "kattis",
      "matchId": "B1",
      "home": 2,
      "away": 1
    },
    {
      "playerId": "kattis",
      "matchId": "B2",
      "home": 2,
      "away": 0
    },
    {
      "playerId": "kattis",
      "matchId": "B3",
      "home": 1,
      "away": 2
    },
    {
      "playerId": "kattis",
      "matchId": "B4",
      "home": 2,
      "away": 1
    },
    {
      "playerId": "kattis",
      "matchId": "B5",
      "home": 0,
      "away": 2
    },
    {
      "playerId": "kattis",
      "matchId": "B6",
      "home": 0,
      "away": 3
    },
    {
      "playerId": "kattis",
      "matchId": "C1",
      "home": 2,
      "away": 1
    },
    {
      "playerId": "kattis",
      "matchId": "C2",
      "home": 4,
      "away": 0
    },
    {
      "playerId": "kattis",
      "matchId": "C3",
      "home": 3,
      "away": 1
    },
    {
      "playerId": "kattis",
      "matchId": "C4",
      "home": 3,
      "away": 0
    },
    {
      "playerId": "kattis",
      "matchId": "C5",
      "home": 2,
      "away": 0
    },
    {
      "playerId": "kattis",
      "matchId": "C6",
      "home": 0,
      "away": 2
    },
    {
      "playerId": "kattis",
      "matchId": "D1",
      "home": 2,
      "away": 0
    },
    {
      "playerId": "kattis",
      "matchId": "D2",
      "home": 2,
      "away": 1
    },
    {
      "playerId": "kattis",
      "matchId": "D3",
      "home": 2,
      "away": 1
    },
    {
      "playerId": "kattis",
      "matchId": "D4",
      "home": 0,
      "away": 1
    },
    {
      "playerId": "kattis",
      "matchId": "D5",
      "home": 1,
      "away": 2
    },
    {
      "playerId": "kattis",
      "matchId": "D6",
      "home": 1,
      "away": 1
    },
    {
      "playerId": "kattis",
      "matchId": "E1",
      "home": 4,
      "away": 0
    },
    {
      "playerId": "kattis",
      "matchId": "E2",
      "home": 2,
      "away": 0
    },
    {
      "playerId": "kattis",
      "matchId": "E3",
      "home": 2,
      "away": 1
    },
    {
      "playerId": "kattis",
      "matchId": "E4",
      "home": 0,
      "away": 2
    },
    {
      "playerId": "kattis",
      "matchId": "E5",
      "home": 1,
      "away": 3
    },
    {
      "playerId": "kattis",
      "matchId": "E6",
      "home": 1,
      "away": 1
    },
    {
      "playerId": "kattis",
      "matchId": "F1",
      "home": 1,
      "away": 1
    },
    {
      "playerId": "kattis",
      "matchId": "F2",
      "home": 2,
      "away": 1
    },
    {
      "playerId": "kattis",
      "matchId": "F3",
      "home": 3,
      "away": 0
    },
    {
      "playerId": "kattis",
      "matchId": "F4",
      "home": 1,
      "away": 1
    },
    {
      "playerId": "kattis",
      "matchId": "F5",
      "home": 2,
      "away": 0
    },
    {
      "playerId": "kattis",
      "matchId": "F6",
      "home": 2,
      "away": 1
    },
    {
      "playerId": "kattis",
      "matchId": "G1",
      "home": 2,
      "away": 1
    },
    {
      "playerId": "kattis",
      "matchId": "G2",
      "home": 1,
      "away": 1
    },
    {
      "playerId": "kattis",
      "matchId": "G3",
      "home": 3,
      "away": 0
    },
    {
      "playerId": "kattis",
      "matchId": "G4",
      "home": 1,
      "away": 1
    },
    {
      "playerId": "kattis",
      "matchId": "G5",
      "home": 2,
      "away": 0
    },
    {
      "playerId": "kattis",
      "matchId": "G6",
      "home": 2,
      "away": 0
    },
    {
      "playerId": "kattis",
      "matchId": "H1",
      "home": 4,
      "away": 0
    },
    {
      "playerId": "kattis",
      "matchId": "H2",
      "home": 3,
      "away": 1
    },
    {
      "playerId": "kattis",
      "matchId": "H3",
      "home": 1,
      "away": 1
    },
    {
      "playerId": "kattis",
      "matchId": "H4",
      "home": 1,
      "away": 1
    },
    {
      "playerId": "kattis",
      "matchId": "H5",
      "home": 1,
      "away": 3
    },
    {
      "playerId": "kattis",
      "matchId": "H6",
      "home": 0,
      "away": 2
    },
    {
      "playerId": "kattis",
      "matchId": "I1",
      "home": 2,
      "away": 1
    },
    {
      "playerId": "kattis",
      "matchId": "I2",
      "home": 3,
      "away": 0
    },
    {
      "playerId": "kattis",
      "matchId": "I3",
      "home": 2,
      "away": 2
    },
    {
      "playerId": "kattis",
      "matchId": "I4",
      "home": 2,
      "away": 0
    },
    {
      "playerId": "kattis",
      "matchId": "I5",
      "home": 1,
      "away": 1
    },
    {
      "playerId": "kattis",
      "matchId": "I6",
      "home": 0,
      "away": 3
    },
    {
      "playerId": "kattis",
      "matchId": "J1",
      "home": 2,
      "away": 1
    },
    {
      "playerId": "kattis",
      "matchId": "J2",
      "home": 2,
      "away": 1
    },
    {
      "playerId": "kattis",
      "matchId": "J3",
      "home": 3,
      "away": 0
    },
    {
      "playerId": "kattis",
      "matchId": "J4",
      "home": 1,
      "away": 2
    },
    {
      "playerId": "kattis",
      "matchId": "J5",
      "home": 2,
      "away": 0
    },
    {
      "playerId": "kattis",
      "matchId": "J6",
      "home": 3,
      "away": 1
    },
    {
      "playerId": "kattis",
      "matchId": "K1",
      "home": 2,
      "away": 0
    },
    {
      "playerId": "kattis",
      "matchId": "K2",
      "home": 2,
      "away": 0
    },
    {
      "playerId": "kattis",
      "matchId": "K3",
      "home": 1,
      "away": 1
    },
    {
      "playerId": "kattis",
      "matchId": "K4",
      "home": 1,
      "away": 1
    },
    {
      "playerId": "kattis",
      "matchId": "K5",
      "home": 0,
      "away": 2
    },
    {
      "playerId": "kattis",
      "matchId": "K6",
      "home": 1,
      "away": 3
    },
    {
      "playerId": "kattis",
      "matchId": "L1",
      "home": 2,
      "away": 1
    },
    {
      "playerId": "kattis",
      "matchId": "L2",
      "home": 2,
      "away": 0
    },
    {
      "playerId": "kattis",
      "matchId": "L3",
      "home": 3,
      "away": 0
    },
    {
      "playerId": "kattis",
      "matchId": "L4",
      "home": 2,
      "away": 1
    },
    {
      "playerId": "kattis",
      "matchId": "L5",
      "home": 2,
      "away": 0
    },
    {
      "playerId": "kattis",
      "matchId": "L6",
      "home": 1,
      "away": 1
    },
    {
      "playerId": "emelie",
      "matchId": "A1",
      "home": 3,
      "away": 2
    },
    {
      "playerId": "emelie",
      "matchId": "A2",
      "home": 2,
      "away": 1
    },
    {
      "playerId": "emelie",
      "matchId": "A3",
      "home": 1,
      "away": 2
    },
    {
      "playerId": "emelie",
      "matchId": "A4",
      "home": 1,
      "away": 2
    },
    {
      "playerId": "emelie",
      "matchId": "A5",
      "home": 1,
      "away": 2
    },
    {
      "playerId": "emelie",
      "matchId": "A6",
      "home": 1,
      "away": 1
    },
    {
      "playerId": "emelie",
      "matchId": "B1",
      "home": 2,
      "away": 1
    },
    {
      "playerId": "emelie",
      "matchId": "B2",
      "home": 1,
      "away": 1
    },
    {
      "playerId": "emelie",
      "matchId": "B3",
      "home": 1,
      "away": 3
    },
    {
      "playerId": "emelie",
      "matchId": "B4",
      "home": 1,
      "away": 2
    },
    {
      "playerId": "emelie",
      "matchId": "B5",
      "home": 1,
      "away": 2
    },
    {
      "playerId": "emelie",
      "matchId": "B6",
      "home": 1,
      "away": 2
    },
    {
      "playerId": "emelie",
      "matchId": "C1",
      "home": 3,
      "away": 1
    },
    {
      "playerId": "emelie",
      "matchId": "C2",
      "home": 4,
      "away": 0
    },
    {
      "playerId": "emelie",
      "matchId": "C3",
      "home": 1,
      "away": 1
    },
    {
      "playerId": "emelie",
      "matchId": "C4",
      "home": 2,
      "away": 1
    },
    {
      "playerId": "emelie",
      "matchId": "C5",
      "home": 0,
      "away": 1
    },
    {
      "playerId": "emelie",
      "matchId": "C6",
      "home": 0,
      "away": 2
    },
    {
      "playerId": "emelie",
      "matchId": "D1",
      "home": 1,
      "away": 1
    },
    {
      "playerId": "emelie",
      "matchId": "D2",
      "home": 2,
      "away": 1
    },
    {
      "playerId": "emelie",
      "matchId": "D3",
      "home": 1,
      "away": 2
    },
    {
      "playerId": "emelie",
      "matchId": "D4",
      "home": 1,
      "away": 0
    },
    {
      "playerId": "emelie",
      "matchId": "D5",
      "home": 0,
      "away": 1
    },
    {
      "playerId": "emelie",
      "matchId": "D6",
      "home": 2,
      "away": 1
    },
    {
      "playerId": "emelie",
      "matchId": "E1",
      "home": 5,
      "away": 0
    },
    {
      "playerId": "emelie",
      "matchId": "E2",
      "home": 3,
      "away": 1
    },
    {
      "playerId": "emelie",
      "matchId": "E3",
      "home": 1,
      "away": 1
    },
    {
      "playerId": "emelie",
      "matchId": "E4",
      "home": 1,
      "away": 3
    },
    {
      "playerId": "emelie",
      "matchId": "E5",
      "home": 0,
      "away": 3
    },
    {
      "playerId": "emelie",
      "matchId": "E6",
      "home": 2,
      "away": 2
    },
    {
      "playerId": "emelie",
      "matchId": "F1",
      "home": 2,
      "away": 1
    },
    {
      "playerId": "emelie",
      "matchId": "F2",
      "home": 2,
      "away": 2
    },
    {
      "playerId": "emelie",
      "matchId": "F3",
      "home": 3,
      "away": 1
    },
    {
      "playerId": "emelie",
      "matchId": "F4",
      "home": 1,
      "away": 2
    },
    {
      "playerId": "emelie",
      "matchId": "F5",
      "home": 1,
      "away": 1
    },
    {
      "playerId": "emelie",
      "matchId": "F6",
      "home": 1,
      "away": 0
    },
    {
      "playerId": "emelie",
      "matchId": "G1",
      "home": 1,
      "away": 1
    },
    {
      "playerId": "emelie",
      "matchId": "G2",
      "home": 2,
      "away": 0
    },
    {
      "playerId": "emelie",
      "matchId": "G3",
      "home": 2,
      "away": 1
    },
    {
      "playerId": "emelie",
      "matchId": "G4",
      "home": 1,
      "away": 0
    },
    {
      "playerId": "emelie",
      "matchId": "G5",
      "home": 2,
      "away": 0
    },
    {
      "playerId": "emelie",
      "matchId": "G6",
      "home": 0,
      "away": 1
    },
    {
      "playerId": "emelie",
      "matchId": "H1",
      "home": 4,
      "away": 1
    },
    {
      "playerId": "emelie",
      "matchId": "H2",
      "home": 3,
      "away": 0
    },
    {
      "playerId": "emelie",
      "matchId": "H3",
      "home": 2,
      "away": 1
    },
    {
      "playerId": "emelie",
      "matchId": "H4",
      "home": 2,
      "away": 2
    },
    {
      "playerId": "emelie",
      "matchId": "H5",
      "home": 0,
      "away": 2
    },
    {
      "playerId": "emelie",
      "matchId": "H6",
      "home": 0,
      "away": 3
    },
    {
      "playerId": "emelie",
      "matchId": "I1",
      "home": 2,
      "away": 1
    },
    {
      "playerId": "emelie",
      "matchId": "I2",
      "home": 2,
      "away": 0
    },
    {
      "playerId": "emelie",
      "matchId": "I3",
      "home": 3,
      "away": 1
    },
    {
      "playerId": "emelie",
      "matchId": "I4",
      "home": 1,
      "away": 0
    },
    {
      "playerId": "emelie",
      "matchId": "I5",
      "home": 1,
      "away": 1
    },
    {
      "playerId": "emelie",
      "matchId": "I6",
      "home": 0,
      "away": 1
    },
    {
      "playerId": "emelie",
      "matchId": "J1",
      "home": 3,
      "away": 0
    },
    {
      "playerId": "emelie",
      "matchId": "J2",
      "home": 3,
      "away": 1
    },
    {
      "playerId": "emelie",
      "matchId": "J3",
      "home": 4,
      "away": 1
    },
    {
      "playerId": "emelie",
      "matchId": "J4",
      "home": 0,
      "away": 1
    },
    {
      "playerId": "emelie",
      "matchId": "J5",
      "home": 1,
      "away": 1
    },
    {
      "playerId": "emelie",
      "matchId": "J6",
      "home": 1,
      "away": 0
    },
    {
      "playerId": "emelie",
      "matchId": "K1",
      "home": 3,
      "away": 0
    },
    {
      "playerId": "emelie",
      "matchId": "K2",
      "home": 4,
      "away": 1
    },
    {
      "playerId": "emelie",
      "matchId": "K3",
      "home": 2,
      "away": 2
    },
    {
      "playerId": "emelie",
      "matchId": "K4",
      "home": 1,
      "away": 0
    },
    {
      "playerId": "emelie",
      "matchId": "K5",
      "home": 0,
      "away": 3
    },
    {
      "playerId": "emelie",
      "matchId": "K6",
      "home": 1,
      "away": 2
    },
    {
      "playerId": "emelie",
      "matchId": "L1",
      "home": 2,
      "away": 0
    },
    {
      "playerId": "emelie",
      "matchId": "L2",
      "home": 2,
      "away": 1
    },
    {
      "playerId": "emelie",
      "matchId": "L3",
      "home": 3,
      "away": 0
    },
    {
      "playerId": "emelie",
      "matchId": "L4",
      "home": 2,
      "away": 1
    },
    {
      "playerId": "emelie",
      "matchId": "L5",
      "home": 3,
      "away": 1
    },
    {
      "playerId": "emelie",
      "matchId": "L6",
      "home": 2,
      "away": 1
    },
    {
      "playerId": "jens",
      "matchId": "A1",
      "home": 2,
      "away": 0
    },
    {
      "playerId": "jens",
      "matchId": "A2",
      "home": 1,
      "away": 1
    },
    {
      "playerId": "jens",
      "matchId": "A3",
      "home": 3,
      "away": 1
    },
    {
      "playerId": "jens",
      "matchId": "A4",
      "home": 0,
      "away": 2
    },
    {
      "playerId": "jens",
      "matchId": "A5",
      "home": 0,
      "away": 1
    },
    {
      "playerId": "jens",
      "matchId": "A6",
      "home": 1,
      "away": 2
    },
    {
      "playerId": "jens",
      "matchId": "B1",
      "home": 2,
      "away": 2
    },
    {
      "playerId": "jens",
      "matchId": "B2",
      "home": 2,
      "away": 0
    },
    {
      "playerId": "jens",
      "matchId": "B3",
      "home": 1,
      "away": 2
    },
    {
      "playerId": "jens",
      "matchId": "B4",
      "home": 3,
      "away": 0
    },
    {
      "playerId": "jens",
      "matchId": "B5",
      "home": 1,
      "away": 1
    },
    {
      "playerId": "jens",
      "matchId": "B6",
      "home": 0,
      "away": 2
    },
    {
      "playerId": "jens",
      "matchId": "C1",
      "home": 2,
      "away": 1
    },
    {
      "playerId": "jens",
      "matchId": "C2",
      "home": 4,
      "away": 0
    },
    {
      "playerId": "jens",
      "matchId": "C3",
      "home": 1,
      "away": 1
    },
    {
      "playerId": "jens",
      "matchId": "C4",
      "home": 3,
      "away": 0
    },
    {
      "playerId": "jens",
      "matchId": "C5",
      "home": 1,
      "away": 2
    },
    {
      "playerId": "jens",
      "matchId": "C6",
      "home": 0,
      "away": 3
    },
    {
      "playerId": "jens",
      "matchId": "D1",
      "home": 2,
      "away": 0
    },
    {
      "playerId": "jens",
      "matchId": "D2",
      "home": 2,
      "away": 1
    },
    {
      "playerId": "jens",
      "matchId": "D3",
      "home": 2,
      "away": 2
    },
    {
      "playerId": "jens",
      "matchId": "D4",
      "home": 1,
      "away": 2
    },
    {
      "playerId": "jens",
      "matchId": "D5",
      "home": 0,
      "away": 2
    },
    {
      "playerId": "jens",
      "matchId": "D6",
      "home": 1,
      "away": 2
    },
    {
      "playerId": "jens",
      "matchId": "E1",
      "home": 6,
      "away": 0
    },
    {
      "playerId": "jens",
      "matchId": "E2",
      "home": 3,
      "away": 1
    },
    {
      "playerId": "jens",
      "matchId": "E3",
      "home": 2,
      "away": 1
    },
    {
      "playerId": "jens",
      "matchId": "E4",
      "home": 0,
      "away": 3
    },
    {
      "playerId": "jens",
      "matchId": "E5",
      "home": 0,
      "away": 2
    },
    {
      "playerId": "jens",
      "matchId": "E6",
      "home": 1,
      "away": 1
    },
    {
      "playerId": "jens",
      "matchId": "F1",
      "home": 3,
      "away": 1
    },
    {
      "playerId": "jens",
      "matchId": "F2",
      "home": 3,
      "away": 1
    },
    {
      "playerId": "jens",
      "matchId": "F3",
      "home": 2,
      "away": 1
    },
    {
      "playerId": "jens",
      "matchId": "F4",
      "home": 1,
      "away": 3
    },
    {
      "playerId": "jens",
      "matchId": "F5",
      "home": 0,
      "away": 2
    },
    {
      "playerId": "jens",
      "matchId": "F6",
      "home": 2,
      "away": 1
    },
    {
      "playerId": "jens",
      "matchId": "G1",
      "home": 1,
      "away": 1
    },
    {
      "playerId": "jens",
      "matchId": "G2",
      "home": 3,
      "away": 0
    },
    {
      "playerId": "jens",
      "matchId": "G3",
      "home": 2,
      "away": 1
    },
    {
      "playerId": "jens",
      "matchId": "G4",
      "home": 2,
      "away": 0
    },
    {
      "playerId": "jens",
      "matchId": "G5",
      "home": 2,
      "away": 0
    },
    {
      "playerId": "jens",
      "matchId": "G6",
      "home": 0,
      "away": 2
    },
    {
      "playerId": "jens",
      "matchId": "H1",
      "home": 6,
      "away": 0
    },
    {
      "playerId": "jens",
      "matchId": "H2",
      "home": 5,
      "away": 0
    },
    {
      "playerId": "jens",
      "matchId": "H3",
      "home": 3,
      "away": 1
    },
    {
      "playerId": "jens",
      "matchId": "H4",
      "home": 1,
      "away": 1
    },
    {
      "playerId": "jens",
      "matchId": "H5",
      "home": 0,
      "away": 3
    },
    {
      "playerId": "jens",
      "matchId": "H6",
      "home": 0,
      "away": 2
    },
    {
      "playerId": "jens",
      "matchId": "I1",
      "home": 3,
      "away": 1
    },
    {
      "playerId": "jens",
      "matchId": "I2",
      "home": 3,
      "away": 0
    },
    {
      "playerId": "jens",
      "matchId": "I3",
      "home": 1,
      "away": 1
    },
    {
      "playerId": "jens",
      "matchId": "I4",
      "home": 2,
      "away": 0
    },
    {
      "playerId": "jens",
      "matchId": "I5",
      "home": 1,
      "away": 2
    },
    {
      "playerId": "jens",
      "matchId": "I6",
      "home": 0,
      "away": 3
    },
    {
      "playerId": "jens",
      "matchId": "J1",
      "home": 2,
      "away": 1
    },
    {
      "playerId": "jens",
      "matchId": "J2",
      "home": 2,
      "away": 0
    },
    {
      "playerId": "jens",
      "matchId": "J3",
      "home": 4,
      "away": 0
    },
    {
      "playerId": "jens",
      "matchId": "J4",
      "home": 1,
      "away": 1
    },
    {
      "playerId": "jens",
      "matchId": "J5",
      "home": 2,
      "away": 0
    },
    {
      "playerId": "jens",
      "matchId": "J6",
      "home": 3,
      "away": 0
    },
    {
      "playerId": "jens",
      "matchId": "K1",
      "home": 5,
      "away": 0
    },
    {
      "playerId": "jens",
      "matchId": "K2",
      "home": 4,
      "away": 0
    },
    {
      "playerId": "jens",
      "matchId": "K3",
      "home": 2,
      "away": 2
    },
    {
      "playerId": "jens",
      "matchId": "K4",
      "home": 1,
      "away": 1
    },
    {
      "playerId": "jens",
      "matchId": "K5",
      "home": 0,
      "away": 2
    },
    {
      "playerId": "jens",
      "matchId": "K6",
      "home": 0,
      "away": 3
    },
    {
      "playerId": "jens",
      "matchId": "L1",
      "home": 2,
      "away": 1
    },
    {
      "playerId": "jens",
      "matchId": "L2",
      "home": 3,
      "away": 1
    },
    {
      "playerId": "jens",
      "matchId": "L3",
      "home": 4,
      "away": 0
    },
    {
      "playerId": "jens",
      "matchId": "L4",
      "home": 2,
      "away": 1
    },
    {
      "playerId": "jens",
      "matchId": "L5",
      "home": 3,
      "away": 0
    },
    {
      "playerId": "jens",
      "matchId": "L6",
      "home": 3,
      "away": 0
    },
    {
      "playerId": "per",
      "matchId": "A1",
      "home": 2,
      "away": 1
    },
    {
      "playerId": "per",
      "matchId": "A2",
      "home": 3,
      "away": 1
    },
    {
      "playerId": "per",
      "matchId": "A3",
      "home": 2,
      "away": 2
    },
    {
      "playerId": "per",
      "matchId": "A4",
      "home": 1,
      "away": 2
    },
    {
      "playerId": "per",
      "matchId": "A5",
      "home": 1,
      "away": 2
    },
    {
      "playerId": "per",
      "matchId": "A6",
      "home": 1,
      "away": 1
    },
    {
      "playerId": "per",
      "matchId": "B1",
      "home": 2,
      "away": 1
    },
    {
      "playerId": "per",
      "matchId": "B2",
      "home": 3,
      "away": 0
    },
    {
      "playerId": "per",
      "matchId": "B3",
      "home": 1,
      "away": 2
    },
    {
      "playerId": "per",
      "matchId": "B4",
      "home": 2,
      "away": 1
    },
    {
      "playerId": "per",
      "matchId": "B5",
      "home": 1,
      "away": 2
    },
    {
      "playerId": "per",
      "matchId": "B6",
      "home": 0,
      "away": 2
    },
    {
      "playerId": "per",
      "matchId": "C1",
      "home": 3,
      "away": 1
    },
    {
      "playerId": "per",
      "matchId": "C2",
      "home": 4,
      "away": 0
    },
    {
      "playerId": "per",
      "matchId": "C3",
      "home": 2,
      "away": 1
    },
    {
      "playerId": "per",
      "matchId": "C4",
      "home": 2,
      "away": 0
    },
    {
      "playerId": "per",
      "matchId": "C5",
      "home": 2,
      "away": 2
    },
    {
      "playerId": "per",
      "matchId": "C6",
      "home": 2,
      "away": 0
    },
    {
      "playerId": "per",
      "matchId": "D1",
      "home": 1,
      "away": 1
    },
    {
      "playerId": "per",
      "matchId": "D2",
      "home": 2,
      "away": 1
    },
    {
      "playerId": "per",
      "matchId": "D3",
      "home": 2,
      "away": 2
    },
    {
      "playerId": "per",
      "matchId": "D4",
      "home": 2,
      "away": 0
    },
    {
      "playerId": "per",
      "matchId": "D5",
      "home": 1,
      "away": 2
    },
    {
      "playerId": "per",
      "matchId": "D6",
      "home": 0,
      "away": 2
    },
    {
      "playerId": "per",
      "matchId": "E1",
      "home": 4,
      "away": 0
    },
    {
      "playerId": "per",
      "matchId": "E2",
      "home": 3,
      "away": 1
    },
    {
      "playerId": "per",
      "matchId": "E3",
      "home": 2,
      "away": 1
    },
    {
      "playerId": "per",
      "matchId": "E4",
      "home": 0,
      "away": 2
    },
    {
      "playerId": "per",
      "matchId": "E5",
      "home": 1,
      "away": 2
    },
    {
      "playerId": "per",
      "matchId": "E6",
      "home": 3,
      "away": 2
    },
    {
      "playerId": "per",
      "matchId": "F1",
      "home": 2,
      "away": 2
    },
    {
      "playerId": "per",
      "matchId": "F2",
      "home": 2,
      "away": 1
    },
    {
      "playerId": "per",
      "matchId": "F3",
      "home": 2,
      "away": 0
    },
    {
      "playerId": "per",
      "matchId": "F4",
      "home": 1,
      "away": 1
    },
    {
      "playerId": "per",
      "matchId": "F5",
      "home": 2,
      "away": 1
    },
    {
      "playerId": "per",
      "matchId": "F6",
      "home": 2,
      "away": 1
    },
    {
      "playerId": "per",
      "matchId": "G1",
      "home": 2,
      "away": 2
    },
    {
      "playerId": "per",
      "matchId": "G2",
      "home": 3,
      "away": 0
    },
    {
      "playerId": "per",
      "matchId": "G3",
      "home": 2,
      "away": 0
    },
    {
      "playerId": "per",
      "matchId": "G4",
      "home": 3,
      "away": 0
    },
    {
      "playerId": "per",
      "matchId": "G5",
      "home": 2,
      "away": 0
    },
    {
      "playerId": "per",
      "matchId": "G6",
      "home": 2,
      "away": 2
    },
    {
      "playerId": "per",
      "matchId": "H1",
      "home": 4,
      "away": 0
    },
    {
      "playerId": "per",
      "matchId": "H2",
      "home": 3,
      "away": 0
    },
    {
      "playerId": "per",
      "matchId": "H3",
      "home": 3,
      "away": 2
    },
    {
      "playerId": "per",
      "matchId": "H4",
      "home": 2,
      "away": 2
    },
    {
      "playerId": "per",
      "matchId": "H5",
      "home": 0,
      "away": 3
    },
    {
      "playerId": "per",
      "matchId": "H6",
      "home": 1,
      "away": 3
    },
    {
      "playerId": "per",
      "matchId": "I1",
      "home": 3,
      "away": 1
    },
    {
      "playerId": "per",
      "matchId": "I2",
      "home": 3,
      "away": 0
    },
    {
      "playerId": "per",
      "matchId": "I3",
      "home": 2,
      "away": 1
    },
    {
      "playerId": "per",
      "matchId": "I4",
      "home": 2,
      "away": 0
    },
    {
      "playerId": "per",
      "matchId": "I5",
      "home": 1,
      "away": 2
    },
    {
      "playerId": "per",
      "matchId": "I6",
      "home": 0,
      "away": 3
    },
    {
      "playerId": "per",
      "matchId": "J1",
      "home": 3,
      "away": 1
    },
    {
      "playerId": "per",
      "matchId": "J2",
      "home": 2,
      "away": 1
    },
    {
      "playerId": "per",
      "matchId": "J3",
      "home": 4,
      "away": 0
    },
    {
      "playerId": "per",
      "matchId": "J4",
      "home": 2,
      "away": 2
    },
    {
      "playerId": "per",
      "matchId": "J5",
      "home": 2,
      "away": 0
    },
    {
      "playerId": "per",
      "matchId": "J6",
      "home": 3,
      "away": 0
    },
    {
      "playerId": "per",
      "matchId": "K1",
      "home": 4,
      "away": 0
    },
    {
      "playerId": "per",
      "matchId": "K2",
      "home": 3,
      "away": 0
    },
    {
      "playerId": "per",
      "matchId": "K3",
      "home": 3,
      "away": 2
    },
    {
      "playerId": "per",
      "matchId": "K4",
      "home": 0,
      "away": 0
    },
    {
      "playerId": "per",
      "matchId": "K5",
      "home": 0,
      "away": 2
    },
    {
      "playerId": "per",
      "matchId": "K6",
      "home": 0,
      "away": 2
    },
    {
      "playerId": "per",
      "matchId": "L1",
      "home": 2,
      "away": 2
    },
    {
      "playerId": "per",
      "matchId": "L2",
      "home": 2,
      "away": 1
    },
    {
      "playerId": "per",
      "matchId": "L3",
      "home": 3,
      "away": 0
    },
    {
      "playerId": "per",
      "matchId": "L4",
      "home": 2,
      "away": 0
    },
    {
      "playerId": "per",
      "matchId": "L5",
      "home": 3,
      "away": 1
    },
    {
      "playerId": "per",
      "matchId": "L6",
      "home": 2,
      "away": 1
    },
    {
      "playerId": "fredrik",
      "matchId": "A1",
      "home": 2,
      "away": 0
    },
    {
      "playerId": "fredrik",
      "matchId": "A2",
      "home": 1,
      "away": 1
    },
    {
      "playerId": "fredrik",
      "matchId": "A3",
      "home": 2,
      "away": 1
    },
    {
      "playerId": "fredrik",
      "matchId": "A4",
      "home": 1,
      "away": 1
    },
    {
      "playerId": "fredrik",
      "matchId": "A5",
      "home": 1,
      "away": 1
    },
    {
      "playerId": "fredrik",
      "matchId": "A6",
      "home": 1,
      "away": 1
    },
    {
      "playerId": "fredrik",
      "matchId": "B1",
      "home": 2,
      "away": 1
    },
    {
      "playerId": "fredrik",
      "matchId": "B2",
      "home": 2,
      "away": 0
    },
    {
      "playerId": "fredrik",
      "matchId": "B3",
      "home": 1,
      "away": 2
    },
    {
      "playerId": "fredrik",
      "matchId": "B4",
      "home": 2,
      "away": 0
    },
    {
      "playerId": "fredrik",
      "matchId": "B5",
      "home": 2,
      "away": 1
    },
    {
      "playerId": "fredrik",
      "matchId": "B6",
      "home": 0,
      "away": 1
    },
    {
      "playerId": "fredrik",
      "matchId": "C1",
      "home": 2,
      "away": 1
    },
    {
      "playerId": "fredrik",
      "matchId": "C2",
      "home": 3,
      "away": 0
    },
    {
      "playerId": "fredrik",
      "matchId": "C3",
      "home": 2,
      "away": 0
    },
    {
      "playerId": "fredrik",
      "matchId": "C4",
      "home": 2,
      "away": 0
    },
    {
      "playerId": "fredrik",
      "matchId": "C5",
      "home": 2,
      "away": 1
    },
    {
      "playerId": "fredrik",
      "matchId": "C6",
      "home": 0,
      "away": 1
    },
    {
      "playerId": "fredrik",
      "matchId": "D1",
      "home": 2,
      "away": 1
    },
    {
      "playerId": "fredrik",
      "matchId": "D2",
      "home": 2,
      "away": 0
    },
    {
      "playerId": "fredrik",
      "matchId": "D3",
      "home": 2,
      "away": 1
    },
    {
      "playerId": "fredrik",
      "matchId": "D4",
      "home": 1,
      "away": 1
    },
    {
      "playerId": "fredrik",
      "matchId": "D5",
      "home": 0,
      "away": 1
    },
    {
      "playerId": "fredrik",
      "matchId": "D6",
      "home": 1,
      "away": 2
    },
    {
      "playerId": "fredrik",
      "matchId": "E1",
      "home": 3,
      "away": 0
    },
    {
      "playerId": "fredrik",
      "matchId": "E2",
      "home": 1,
      "away": 2
    },
    {
      "playerId": "fredrik",
      "matchId": "E3",
      "home": 1,
      "away": 1
    },
    {
      "playerId": "fredrik",
      "matchId": "E4",
      "home": 0,
      "away": 2
    },
    {
      "playerId": "fredrik",
      "matchId": "E5",
      "home": 0,
      "away": 2
    },
    {
      "playerId": "fredrik",
      "matchId": "E6",
      "home": 1,
      "away": 1
    },
    {
      "playerId": "fredrik",
      "matchId": "F1",
      "home": 1,
      "away": 2
    },
    {
      "playerId": "fredrik",
      "matchId": "F2",
      "home": 2,
      "away": 1
    },
    {
      "playerId": "fredrik",
      "matchId": "F3",
      "home": 2,
      "away": 0
    },
    {
      "playerId": "fredrik",
      "matchId": "F4",
      "home": 1,
      "away": 1
    },
    {
      "playerId": "fredrik",
      "matchId": "F5",
      "home": 2,
      "away": 0
    },
    {
      "playerId": "fredrik",
      "matchId": "F6",
      "home": 2,
      "away": 1
    },
    {
      "playerId": "fredrik",
      "matchId": "G1",
      "home": 2,
      "away": 1
    },
    {
      "playerId": "fredrik",
      "matchId": "G2",
      "home": 2,
      "away": 0
    },
    {
      "playerId": "fredrik",
      "matchId": "G3",
      "home": 3,
      "away": 0
    },
    {
      "playerId": "fredrik",
      "matchId": "G4",
      "home": 1,
      "away": 0
    },
    {
      "playerId": "fredrik",
      "matchId": "G5",
      "home": 2,
      "away": 0
    },
    {
      "playerId": "fredrik",
      "matchId": "G6",
      "home": 1,
      "away": 0
    },
    {
      "playerId": "fredrik",
      "matchId": "H1",
      "home": 2,
      "away": 0
    },
    {
      "playerId": "fredrik",
      "matchId": "H2",
      "home": 3,
      "away": 0
    },
    {
      "playerId": "fredrik",
      "matchId": "H3",
      "home": 1,
      "away": 1
    },
    {
      "playerId": "fredrik",
      "matchId": "H4",
      "home": 1,
      "away": 1
    },
    {
      "playerId": "fredrik",
      "matchId": "H5",
      "home": 0,
      "away": 2
    },
    {
      "playerId": "fredrik",
      "matchId": "H6",
      "home": 0,
      "away": 2
    },
    {
      "playerId": "fredrik",
      "matchId": "I1",
      "home": 2,
      "away": 1
    },
    {
      "playerId": "fredrik",
      "matchId": "I2",
      "home": 3,
      "away": 0
    },
    {
      "playerId": "fredrik",
      "matchId": "I3",
      "home": 2,
      "away": 1
    },
    {
      "playerId": "fredrik",
      "matchId": "I4",
      "home": 2,
      "away": 0
    },
    {
      "playerId": "fredrik",
      "matchId": "I5",
      "home": 1,
      "away": 1
    },
    {
      "playerId": "fredrik",
      "matchId": "I6",
      "home": 0,
      "away": 2
    },
    {
      "playerId": "fredrik",
      "matchId": "J1",
      "home": 2,
      "away": 0
    },
    {
      "playerId": "fredrik",
      "matchId": "J2",
      "home": 1,
      "away": 1
    },
    {
      "playerId": "fredrik",
      "matchId": "J3",
      "home": 3,
      "away": 0
    },
    {
      "playerId": "fredrik",
      "matchId": "J4",
      "home": 1,
      "away": 1
    },
    {
      "playerId": "fredrik",
      "matchId": "J5",
      "home": 2,
      "away": 0
    },
    {
      "playerId": "fredrik",
      "matchId": "J6",
      "home": 2,
      "away": 0
    },
    {
      "playerId": "fredrik",
      "matchId": "K1",
      "home": 2,
      "away": 0
    },
    {
      "playerId": "fredrik",
      "matchId": "K2",
      "home": 2,
      "away": 0
    },
    {
      "playerId": "fredrik",
      "matchId": "K3",
      "home": 1,
      "away": 2
    },
    {
      "playerId": "fredrik",
      "matchId": "K4",
      "home": 1,
      "away": 1
    },
    {
      "playerId": "fredrik",
      "matchId": "K5",
      "home": 0,
      "away": 2
    },
    {
      "playerId": "fredrik",
      "matchId": "K6",
      "home": 1,
      "away": 1
    },
    {
      "playerId": "fredrik",
      "matchId": "L1",
      "home": 2,
      "away": 1
    },
    {
      "playerId": "fredrik",
      "matchId": "L2",
      "home": 2,
      "away": 1
    },
    {
      "playerId": "fredrik",
      "matchId": "L3",
      "home": 3,
      "away": 0
    },
    {
      "playerId": "fredrik",
      "matchId": "L4",
      "home": 1,
      "away": 1
    },
    {
      "playerId": "fredrik",
      "matchId": "L5",
      "home": 2,
      "away": 0
    },
    {
      "playerId": "fredrik",
      "matchId": "L6",
      "home": 2,
      "away": 0
    }
  ]
}